cogit/__init__.py
cogit/defaults.py
cogit/main.py
py_cogit-0.1.1.dist-info/licenses/LICENSE
py_cogit-0.1.1.dist-info/METADATA
py_cogit-0.1.1.dist-info/WHEEL
py_cogit-0.1.1.dist-info/entry_points.txt
py_cogit-0.1.1.dist-info/top_level.txt
py_cogit-0.1.1.dist-info/RECORD
