Metadata-Version: 2.4
Name: py-cogit
Version: 0.1.1
Summary: A command-line tool for code analysis.
Author-email: Andrei Silva <andrei.fbds@gmail.com>
Classifier: Programming Language :: Python :: 3
Classifier: License :: OSI Approved :: MIT License
Classifier: Operating System :: OS Independent
Requires-Python: >=3.8
License-File: LICENSE
Requires-Dist: python-dotenv
Requires-Dist: google-generativeai
Dynamic: license-file
